Airpeak/__init__.py
Airpeak/baseline_detection.py
Airpeak/dbscan.py
Airpeak/decay_regress.py
Airpeak/feature_generation.py
Airpeak/k_means_diff.py
Airpeak/k_means_ele.py
Airpeak/outlier_removal.py
Airpeak/smoothing.py
airpeak-1.0.5.dist-info/licenses/LICENSE
airpeak-1.0.5.dist-info/METADATA
airpeak-1.0.5.dist-info/WHEEL
airpeak-1.0.5.dist-info/top_level.txt
airpeak-1.0.5.dist-info/RECORD
