Metadata-Version: 2.4
Name: airpeak
Version: 1.0.5
Summary: A Python package for recognizing build-up and decay events from pollutant concentration data and estimating pollutant loss rates.
Requires-Python: <3.14,>=3.10
License-File: LICENSE
Requires-Dist: datetime>=5.5
Requires-Dist: matplotlib>=3.10.1
Requires-Dist: numpy>=2.2.5
Requires-Dist: pandas>=2.2.3
Requires-Dist: scikit-learn>=1.6.1
Requires-Dist: scipy>=1.15.2
Requires-Dist: seaborn>=0.13.2
Provides-Extra: docs
Requires-Dist: sphinx>=7.2; extra == "docs"
Requires-Dist: furo>=2024.1.29; extra == "docs"
Requires-Dist: sphinx-autodoc-typehints; extra == "docs"
Requires-Dist: sphinxcontrib-napoleon; extra == "docs"
Dynamic: license-file
